odoo/addons/product_attribute_set/README.rst
odoo/addons/product_attribute_set/__init__.py
odoo/addons/product_attribute_set/__manifest__.py
odoo/addons/product_attribute_set/demo/product_attribute.xml
odoo/addons/product_attribute_set/i18n/product_attribute_set.pot
odoo/addons/product_attribute_set/models/__init__.py
odoo/addons/product_attribute_set/models/product.py
odoo/addons/product_attribute_set/models/product_category.py
odoo/addons/product_attribute_set/models/res_company.py
odoo/addons/product_attribute_set/readme/CONTRIBUTORS.rst
odoo/addons/product_attribute_set/readme/DESCRIPTION.rst
odoo/addons/product_attribute_set/readme/ROADMAP.rst
odoo/addons/product_attribute_set/readme/USAGE.rst
odoo/addons/product_attribute_set/static/description/icon.png
odoo/addons/product_attribute_set/static/description/index.html
odoo/addons/product_attribute_set/views/product.xml
odoo/addons/product_attribute_set/views/product_category.xml
odoo12_addon_product_attribute_set-12.0.2.1.0.99.dev7.dist-info/METADATA
odoo12_addon_product_attribute_set-12.0.2.1.0.99.dev7.dist-info/WHEEL
odoo12_addon_product_attribute_set-12.0.2.1.0.99.dev7.dist-info/top_level.txt
odoo12_addon_product_attribute_set-12.0.2.1.0.99.dev7.dist-info/RECORD
